nqrduck_measurement/__init__.py
nqrduck_measurement/controller.py
nqrduck_measurement/measurement.py
nqrduck_measurement/model.py
nqrduck_measurement/signalprocessing_options.py
nqrduck_measurement/view.py
nqrduck_measurement/widget.py
nqrduck_measurement/resources/measurement_widget.ui
nqrduck_measurement/resources/mesurement.ini
nqrduck_measurement-0.0.7.dist-info/METADATA
nqrduck_measurement-0.0.7.dist-info/WHEEL
nqrduck_measurement-0.0.7.dist-info/entry_points.txt
nqrduck_measurement-0.0.7.dist-info/licenses/LICENSE
nqrduck_measurement-0.0.7.dist-info/RECORD
