Metadata-Version: 2.4
Name: nqrduck-measurement
Version: 0.0.7
Summary: A module for the NQRduck program (a simple python script™) to perform single frequency measurements.
Project-URL: Homepage, https://nqrduck.cool
Project-URL: Bug Tracker, https://git.private.coffee/nqrduck/nqrduck-measurement/issues
Project-URL: Source Code, https://git.private.coffee/nqrduck/nqrduck-measurement
Author-email: jupfi <support@nqrduck.cool>
License: MIT License
License-File: LICENSE
Classifier: License :: OSI Approved :: MIT License
Classifier: Operating System :: OS Independent
Classifier: Programming Language :: Python :: 3
Requires-Python: >=3.10
Requires-Dist: matplotlib
Requires-Dist: nqrduck
Requires-Dist: nqrduck-pulseprogrammer
Requires-Dist: nqrduck-spectrometer
Requires-Dist: pyqt6
Requires-Dist: quackseq
Requires-Dist: sympy
Provides-Extra: dev
Requires-Dist: black; extra == 'dev'
Requires-Dist: pydocstyle; extra == 'dev'
Requires-Dist: pyupgrade; extra == 'dev'
Requires-Dist: ruff; extra == 'dev'
